{
    "configurations": [
        {
            "name": "Mac",
            "includePath": [
                "${workspaceFolder}/cpp/include/*",
                "${workspaceFolder}/cpp/lib/*",
                "${workspaceFolder}/cpp/lib/rapidjson/*"
            ],
            "defines": [],
            "macFrameworkPath": [
                "/System/Library/Frameworks",
                "/Library/Frameworks"
            ],
            "compilerPath": "/usr/bin/clang",
            "intelliSenseMode": "clang-x64"
        }
    ],
    "version": 4
}